voc_tools/__init__.py
voc_tools/constants.py
voc_tools/reader.py
voc_tools/utils.py
voc_tools/visulizer.py
voc_tools/writer.py
voc_tools/unittest/__init__.py
voc_tools/unittest/reader_test.py
express_pascal_voc_tools-0.7.3.dist-info/LICENSE
express_pascal_voc_tools-0.7.3.dist-info/METADATA
express_pascal_voc_tools-0.7.3.dist-info/WHEEL
express_pascal_voc_tools-0.7.3.dist-info/top_level.txt
express_pascal_voc_tools-0.7.3.dist-info/RECORD
