Metadata-Version: 2.1
Name: express-pascal-voc-tools
Version: 0.7.3
Summary: A tool for creating, reading and visualizing Pascal VOC annotations
Author: Soumen Sardar
Author-email: soumensardarintmain@gmail.com
Classifier: Programming Language :: Python :: 3
Classifier: License :: OSI Approved :: GNU General Public License v3 (GPLv3)
Classifier: Operating System :: OS Independent
Requires-Python: >=3.6
License-File: LICENSE
Requires-Dist: lxml
Requires-Dist: numpy
Requires-Dist: opencv-python
